document_theft/__init__.py
document_theft/main.py
youtube_theft_documenter-0.1.0.dist-info/METADATA
youtube_theft_documenter-0.1.0.dist-info/WHEEL
youtube_theft_documenter-0.1.0.dist-info/entry_points.txt
youtube_theft_documenter-0.1.0.dist-info/top_level.txt
youtube_theft_documenter-0.1.0.dist-info/RECORD
